{"schemaVersion":"1.0"}
{"id":1595700445414,"params":"{city_id=[280]}","username":null}
{"id":1595700447322,"params":"{city_id=[280]}","username":null}
{"id":1595700448269,"params":"{city_id=[280]}","username":null}
{"id":1595700613042,"params":"{city_id=[280]}","username":null}
{"id":1595701253346,"params":"{city_id=[280]}","username":"ronal2"}
{"id":1595701261896,"params":"{city_id=[280]}","username":"ronal2"}
{"id":1595702164269,"params":"{city_id=[280]}","username":"ronal2"}
{"id":1595702686666,"params":"{city_id=[280]}","username":"ronal2"}
{"id":1595702728964,"params":"{city_id=[280]}","username":"ronal2"}
{"id":1595702744579,"params":"{city_id=[280]}","username":"ronal2"}
{"id":1595702746295,"params":"{city_id=[280]}","username":"ronal2"}
{"id":1595702747328,"params":"{city_id=[280]}","username":"ronal2"}
